yttran/__init__.py
yttran/cli.py
yttran-0.2.2.dist-info/WHEEL
yttran-0.2.2.dist-info/entry_points.txt
yttran-0.2.2.dist-info/METADATA
yttran-0.2.2.dist-info/RECORD
