Metadata-Version: 2.3
Name: yttran
Version: 0.2.2
Summary: A simple CLI to fetch plain text transcripts in english from YouTube videos. Powered by youtube-transcript-api. Cached to local disk.
Keywords: youtube,transcript,cli,command line,tool,video,subtitle,captions
Author: Rudiger Wolf
Author-email: Rudiger Wolf <rudiger.wolf@throughputfocus.com>
License: # The MIT License (MIT)
Classifier: Programming Language :: Python :: 3
Classifier: License :: OSI Approved :: MIT License
Classifier: Operating System :: OS Independent
Requires-Dist: youtube-transcript-api>=0.6.2
Requires-Python: >=3.8
Project-URL: Homepage, https://github.com/rnwolf/yttran
Project-URL: Repository, https://github.com/rnwolf/yttran.git
